annxuncements/__init__.py
annxuncements/announcement_subscription.py
annxuncements/announcements.py
annxuncements/announcer.py
annxuncements/subscription_registry.py
annxuncements-0.0.1.dist-info/LICENSE
annxuncements-0.0.1.dist-info/METADATA
annxuncements-0.0.1.dist-info/WHEEL
annxuncements-0.0.1.dist-info/top_level.txt
annxuncements-0.0.1.dist-info/RECORD
